setup.py
matrix_algebra/__init__.py
matrix_algebra/python_code.py
matrix_algebra.egg-info/PKG-INFO
matrix_algebra.egg-info/SOURCES.txt
matrix_algebra.egg-info/dependency_links.txt
matrix_algebra.egg-info/not-zip-safe
matrix_algebra.egg-info/top_level.txt