Metadata-Version: 1.0
Name: matrix-algebra
Version: 0.1
Summary: Computation matrix
Home-page: UNKNOWN
Author: Charles Cirotteau
Author-email: charles.cirotteau@free.fr
License: UNKNOWN
Platform: UNKNOWN
